LICENSE
README.md
dist.json
setup.py
lib/distman/__init__.py
lib/distman/cli.py
lib/distman/config.py
lib/distman/dist.py
lib/distman/logger.py
lib/distman/pipeline.py
lib/distman/source.py
lib/distman/transform.py
lib/distman/util.py
lib/distman.egg-info/PKG-INFO
lib/distman.egg-info/SOURCES.txt
lib/distman.egg-info/dependency_links.txt
lib/distman.egg-info/entry_points.txt
lib/distman.egg-info/not-zip-safe
lib/distman.egg-info/requires.txt
lib/distman.egg-info/top_level.txt
tests/test_dist.py
tests/test_pipeline.py
tests/test_transform.py
tests/test_util.py