Metadata-Version: 2.1
Name: distman
Version: 0.6.1
Summary: Simple software distribution for complex pipelines
Home-page: http://github.com/rsgalloway/distman
Author: Ryan Galloway
Author-email: ryan@rsgalloway.com
License: BSD 3-Clause License
Classifier: Development Status :: 4 - Beta
Classifier: Intended Audience :: Developers
Classifier: Topic :: Software Development :: Libraries
Classifier: Programming Language :: Python :: 3
Classifier: Programming Language :: Python :: 3.6
Classifier: Programming Language :: Python :: 3.7
Classifier: Programming Language :: Python :: 3.8
Classifier: Programming Language :: Python :: 3.9
Classifier: Programming Language :: Python :: 3.10
Classifier: Programming Language :: Python :: 3.11
Requires-Python: >=3.6
License-File: LICENSE
Requires-Dist: GitPython==3.1.43
Requires-Dist: htmlmin==0.1.12
Requires-Dist: jsmin==3.0.1
Requires-Dist: dataclasses; python_version < "3.7"
